Handshake Mechanism/src/handshake_mechanism.sv
///////////////////////////////////////////////////////////
//
//        Handshake Synchronizer Mechanism RTL Design
//
//        Author: Mahmoud Magdi 
//
///////////////////////////////////////////////////////////



module handshake_mechanism #(

    parameter DATA_WIDTH = 8

) (
    
    input   logic                        i_clk_a    ,                             // Source      Domain Clock 
    input   logic                        i_clk_b    ,                             // Destination Domain Clock 
    input   logic                        i_rst_n_a  ,                             // Active-Low asynchronous source      reset
    input   logic                        i_rst_n_b  ,                             // Active-Low asynchronous destination reset
    input   logic                        i_valid    ,                             // Input valid Signal indicating a valid data to be sent from d1 to d2
    input   logic   [DATA_WIDTH - 1 : 0] i_data     ,                             // Data that cosses from Domain 1 to Domain 2
    output  logic                        o_busy     ,
    output  logic                        o_valid    ,
    output  logic   [DATA_WIDTH - 1 : 0] o_data                                   // Synchronized output Data 

);


logic                      REQ, ACK, Sync_REQ, Sync_ACK, req_sync_0, ack_sync_0;
logic [DATA_WIDTH - 1 : 0] data_sync;


typedef enum logic { IDLE, WAIT } state;

state current_state, next_state;

assign o_busy = current_state;


//////////////////////////////////////////////////////
/// ---------------   Sender FSM   --------------- ///
//////////////////////////////////////////////////////

always_ff @( posedge i_clk_a or negedge i_rst_n_a ) begin : current_state_logic 
    
    if (!i_rst_n_a) begin

        current_state <= IDLE;

    end else begin

        current_state <= next_state;

    end

end


always_comb begin : next_state_logic
    
    case (current_state)

        IDLE: begin

            if (i_valid == 1'b1) begin

                next_state = WAIT;

            end else begin

                next_state = IDLE;

            end

        end
    
        WAIT: begin
            
            if (!(REQ ^ Sync_ACK)) begin

                next_state = IDLE;

            end else begin

                next_state = WAIT;
                
            end

        end 
    
        default: next_state = IDLE;
    
    endcase

end


////////////////////////////////////////////////////////////////////////
/// -------------   REQ Generation and Data Sampling   ------------- ///
////////////////////////////////////////////////////////////////////////

always_ff @( posedge i_clk_a or negedge i_rst_n_a ) begin : REQ_GENERATOR
    
    if (!i_rst_n_a) begin

        REQ       <= 'b0;
        data_sync <= 'b0;

    end else if( (!o_busy) && i_valid ) begin

        REQ       <= ~REQ;
        data_sync <= i_data;

    end

end



//////////////////////////////////////////////////////
/// ------------ REQ Synchronization ------------- ///
//////////////////////////////////////////////////////

always_ff @( posedge i_clk_b or negedge i_rst_n_b ) begin : REQ_Synchronizer 

   if (!i_rst_n_b) begin

        req_sync_0  <= 1'b0;
        Sync_REQ    <= 1'b0;

   end else begin

        req_sync_0  <= REQ;
        Sync_REQ    <= req_sync_0;

   end

end



//////////////////////////////////////////////////////
/// ------------ ACK Synchronization ------------- ///
//////////////////////////////////////////////////////

always_ff @( posedge i_clk_a or negedge i_rst_n_a ) begin : ACK_Synchronizer 

   if (!i_rst_n_a) begin

        ack_sync_0  <= 1'b0;
        Sync_ACK    <= 1'b0;

   end else begin

        ack_sync_0  <= ACK;
        Sync_ACK    <= ack_sync_0;

   end

end



////////////////////////////////////////////////////////////////////////
/// -------------   ACK Generation and Data Fetching   ------------- ///
////////////////////////////////////////////////////////////////////////

always_ff @( posedge i_clk_b or negedge i_rst_n_b ) begin : ACK_AND_OUTPUT
    
    if (!i_rst_n_b) begin
        
        ACK     <= 'b0;
        o_valid <= 'b0;
        o_data  <= 'b0;

    end else if(Sync_REQ ^ ACK) begin
        
        ACK     <= ~ACK;
        o_valid <= 1'b1;
        o_data  <= data_sync;

    end else begin
        
        o_valid <= 'b0;

    end

end
endmodule

Handshake Mechanism/tb/handshake_tb.sv
module handshake_tb #(

    parameter DATA_WIDTH = 8

);


logic                           i_clk_a;
logic                           i_clk_b;
logic                           rstn   ;
logic   [DATA_WIDTH - 1 : 0]    i_data ;
logic                           i_valid;
logic                           o_busy ;
logic                           o_valid;
logic   [DATA_WIDTH - 1 : 0]    o_data ;

logic   [DATA_WIDTH - 1 : 0]   expected [99:0];
logic   [DATA_WIDTH - 1 : 0]   result   [99:0];
logic   [DATA_WIDTH - 1 : 0]   ref_data;

int o_count, i_count;


handshake_mechanism #(
    
    .DATA_WIDTH(DATA_WIDTH)
    
) dut (

    .i_clk_a   (i_clk_a ), 
    .i_clk_b   (i_clk_b ), 
    .i_rst_n_a (rstn    ),
    .i_rst_n_b (rstn    ),
    .i_data    (i_data  ),
    .i_valid   (i_valid ),
    .o_busy    (o_busy  ),
    .o_valid   (o_valid ),
    .o_data    (o_data  )

);

always #5 i_clk_a  = ~i_clk_a;
always #13 i_clk_b = ~i_clk_b;


task send_data();
begin
    ref_data = $random;
    @(posedge i_clk_a);
    i_valid <= 1;
    i_data  <= ref_data;
    @(posedge i_clk_a);
    i_valid <= 0;
end
endtask

initial begin

    $dumpfile("handshake.vcd");
    $dumpvars(0,handshake_tb);

    i_count = 0;
    o_count = 0;
    i_clk_a = 0;
    i_clk_b = 0;
    rstn    = 1;

    #1 rstn = 0;
    #2 rstn = 1;
    for (int i = 0; i < 500; i++) begin
        send_data();
    end
    #500 $stop;
end

always @(posedge i_clk_a) begin
    if(~o_busy & i_valid) begin
        expected[i_count] <= i_data;
        i_count = i_count + 1;
    end
end

always @(posedge o_valid) begin
    #1 result[o_count]     = o_data;
    #1 if(result[o_count] != expected[o_count]) begin
        $display("expected = %d     result = %d failed at time %t",expected[o_count], result[o_count], $time);
    end 
    else begin
        $display("expected = %d     result = %d",expected[o_count], result[o_count]);
    end

    #1 o_count = o_count + 1;
end

endmodule

Handshake Mechanism/VCD Files/handshake_tb.vcd
$date
	Wed Feb 28 01:40:19 2024
$end
$version
	QuestaSim Version 2021.1
$end
$timescale
	1ns
$end

$scope module handshake_tb $end
$var parameter 32 ! DATA_WIDTH $end
$var reg 1 " i_clk_a $end
$var reg 1 # i_clk_b $end
$var reg 1 $ rstn $end
$var reg 8 % i_data [7:0] $end
$var reg 1 & i_valid $end
$var reg 1 ' o_busy $end
$var reg 1 ( o_valid $end
$var reg 8 ) o_data [7:0] $end
$var reg 8 * ref_data [7:0] $end
$var integer 32 + o_count $end
$var integer 32 , i_count $end

$scope task send_data $end
$upscope $end
$upscope $end
$enddefinitions $end
#0
$dumpvars
0"
0#
1$
bx %
x&
x'
x(
bx )
bx *
b1000 !
b0 +
b0 ,
$end
#1
0$
b0 )
0(
0'
#3
1$
b100100 *
#5
1"
1&
b100100 %
#10
0"
#13
1#
#15
1"
b1 ,
b10000001 *
0&
1'
#20
0"
#25
1"
1&
b10000001 %
#26
0#
#30
0"
#35
1"
b1001 *
0&
#39
1#
#40
0"
#45
1"
1&
b1001 %
#50
0"
#52
0#
#55
1"
b1100011 *
0&
#60
0"
#65
1#
1"
1&
b1100011 %
#70
0"
#75
1"
b1101 *
0&
#78
0#
#80
0"
#85
1"
1&
b1101 %
#90
0"
#91
1#
b100100 )
1(
#94
b1 +
#95
1"
b10001101 *
0&
#100
0"
#104
0#
#105
1"
1&
b10001101 %
#110
0"
#115
1"
b1100101 *
0&
0'
#117
1#
0(
#120
0"
#125
1"
1&
b1100101 %
#130
0#
0"
#135
1"
b10 ,
b10010 *
0&
1'
#140
0"
#143
1#
#145
1"
1&
b10010 %
#150
0"
#155
1"
b1 *
0&
#156
0#
#160
0"
#165
1"
1&
b1 %
#169
1#
#170
0"
#175
1"
b1101 *
0&
#180
0"
#182
0#
#185
1"
1&
b1101 %
#190
0"
#195
1#
1"
b1110110 *
0&
b1100101 )
1(
#198
b10 +
#200
0"
#205
1"
1&
b1110110 %
#208
0#
#210
0"
#215
1"
b111101 *
0&
#220
0"
#221
1#
0(
#225
1"
1&
b111101 %
0'
#230
0"
#234
0#
#235
1"
b11 ,
b11101101 *
0&
1'
#240
0"
#245
1"
1&
b11101101 %
#247
1#
#250
0"
#255
1"
b10001100 *
0&
#260
0#
0"
#265
1"
1&
b10001100 %
#270
0"
#273
1#
#275
1"
b11111001 *
0&
#280
0"
#285
1"
1&
b11111001 %
#286
0#
#290
0"
#295
1"
b11000110 *
0&
#299
1#
b111101 )
1(
#300
0"
#302
b11 +
#305
1"
1&
b11000110 %
#310
0"
#312
0#
#315
1"
b11000101 *
0&
#320
0"
#325
1#
1"
1&
b11000101 %
0(
0'
#330
0"
#335
1"
b100 ,
b10101010 *
0&
1'
#338
0#
#340
0"
#345
1"
1&
b10101010 %
#350
0"
#351
1#
#355
1"
b11100101 *
0&
#360
0"
#364
0#
#365
1"
1&
b11100101 %
#370
0"
#375
1"
b1110111 *
0&
#377
1#
#380
0"
#385
1"
1&
b1110111 %
#390
0#
0"
#395
1"
b10010 *
0&
#400
0"
#403
1#
b11000101 )
1(
#405
1"
1&
b10010 %
#406
b100 +
#410
0"
#415
1"
b10001111 *
0&
#416
0#
#420
0"
#425
1"
1&
b10001111 %
0'
#429
1#
0(
#430
0"
#435
1"
b101 ,
b11110010 *
0&
1'
#440
0"
#442
0#
#445
1"
1&
b11110010 %
#450
0"
#455
1#
1"
b11001110 *
0&
#460
0"
#465
1"
1&
b11001110 %
#468
0#
#470
0"
#475
1"
b11101000 *
0&
#480
0"
#481
1#
#485
1"
1&
b11101000 %
#490
0"
#494
0#
#495
1"
b11000101 *
0&
#500
0"
#505
1"
1&
b11000101 %
#507
1#
b10001111 )
1(
#510
0"
b101 +
#515
1"
b1011100 *
0&
#520
0#
0"
#525
1"
1&
b1011100 %
#530
0"
#533
1#
0(
#535
1"
b10111101 *
0&
0'
#540
0"
#545
1"
1&
b10111101 %
#546
0#
#550
0"
#555
1"
b110 ,
b101101 *
0&
1'
#559
1#
#560
0"
#565
1"
1&
b101101 %
#570
0"
#572
0#
#575
1"
b1100101 *
0&
#580
0"
#585
1#
1"
1&
b1100101 %
#590
0"
#595
1"
b1100011 *
0&
#598
0#
#600
0"
#605
1"
1&
b1100011 %
#610
0"
#611
1#
b10111101 )
1(
#614
b110 +
#615
1"
b1010 *
0&
#620
0"
#624
0#
#625
1"
1&
b1010 %
#630
0"
#635
1"
b10000000 *
0&
0'
#637
1#
0(
#640
0"
#645
1"
1&
b10000000 %
#650
0#
0"
#655
1"
b111 ,
b100000 *
0&
1'
#660
0"
#663
1#
#665
1"
1&
b100000 %
#670
0"
#675
1"
b10101010 *
0&
#676
0#
#680
0"
#685
1"
1&
b10101010 %
#689
1#
#690
0"
#695
1"
b10011101 *
0&
#700
0"
#702
0#
#705
1"
1&
b10011101 %
#710
0"
#715
1#
1"
b10010110 *
0&
b10000000 )
1(
#718
b111 +
#720
0"
#725
1"
1&
b10010110 %
#728
0#
#730
0"
#735
1"
b10011 *
0&
#740
0"
#741
1#
0(
#745
1"
1&
b10011 %
0'
#750
0"
#754
0#
#755
1"
b1000 ,
b1101 *
0&
1'
#760
0"
#765
1"
1&
b1101 %
#767
1#
#770
0"
#775
1"
b1010011 *
0&
#780
0#
0"
#785
1"
1&
b1010011 %
#790
0"
#793
1#
#795
1"
b1101011 *
0&
#800
0"
#805
1"
1&
b1101011 %
#806
0#
#810
0"
#815
1"
b11010101 *
0&
#819
1#
b10011 )
1(
#820
0"
#822
b1000 +
#825
1"
1&
b11010101 %
#830
0"
#832
0#
#835
1"
b10 *
0&
#840
0"
#845
1#
1"
1&
b10 %
0(
0'
#850
0"
#855
1"
b1001 ,
b10101110 *
0&
1'
#858
0#
#860
0"
#865
1"
1&
b10101110 %
#870
0"
#871
1#
#875
1"
b11101 *
0&
#880
0"
#884
0#
#885
1"
1&
b11101 %
#890
0"
#895
1"
b11001111 *
0&
#897
1#
#900
0"
#905
1"
1&
b11001111 %
#910
0#
0"
#915
1"
b100011 *
0&
#920
0"
#923
1#
b10 )
1(
#925
1"
1&
b100011 %
#926
b1001 +
#930
0"
#935
1"
b1010 *
0&
#936
0#
#940
0"
#945
1"
1&
b1010 %
0'
#949
1#
0(
#950
0"
#955
1"
b1010 ,
b11001010 *
0&
1'
#960
0"
#962
0#
#965
1"
1&
b11001010 %
#970
0"
#975
1#
1"
b111100 *
0&
#980
0"
#985
1"
1&
b111100 %
#988
0#
#990
0"
#995
1"
b11110010 *
0&
#1000
0"
#1001
1#
#1005
1"
1&
b11110010 %
#1010
0"
#1014
0#
#1015
1"
b10001010 *
0&
#1020
0"
#1025
1"
1&
b10001010 %
#1027
1#
b1010 )
1(
#1030
0"
b1010 +
#1035
1"
b1000001 *
0&
#1040
0#
0"
#1045
1"
1&
b1000001 %
#1050
0"
#1053
1#
0(
#1055
1"
b11011000 *
0&
0'
#1060
0"
#1065
1"
1&
b11011000 %
#1066
0#
#1070
0"
#1075
1"
b1011 ,
b1111000 *
0&
1'
#1079
1#
#1080
0"
#1085
1"
1&
b1111000 %
#1090
0"
#1092
0#
#1095
1"
b10001001 *
0&
#1100
0"
#1105
1#
1"
1&
b10001001 %
#1110
0"
#1115
1"
b11101011 *
0&
#1118
0#
#1120
0"
#1125
1"
1&
b11101011 %
#1130
0"
#1131
1#
b11011000 )
1(
#1134
b1011 +
#1135
1"
b10110110 *
0&
#1140
0"
#1144
0#
#1145
1"
1&
b10110110 %
#1150
0"
#1155
1"
b11000110 *
0&
0'
#1157
1#
0(
#1160
0"
#1165
1"
1&
b11000110 %
#1170
0#
0"
#1175
1"
b1100 ,
b10101110 *
0&
1'
#1180
0"
#1183
1#
#1185
1"
1&
b10101110 %
#1190
0"
#1195
1"
b10111100 *
0&
#1196
0#
#1200
0"
#1205
1"
1&
b10111100 %
#1209
1#
#1210
0"
#1215
1"
b101010 *
0&
#1220
0"
#1222
0#
#1225
1"
1&
b101010 %
#1230
0"
#1235
1#
1"
b1011 *
0&
b11000110 )
1(
#1238
b1100 +
#1240
0"
#1245
1"
1&
b1011 %
#1248
0#
#1250
0"
#1255
1"
b1110001 *
0&
#1260
0"
#1261
1#
0(
#1265
1"
1&
b1110001 %
0'
#1270
0"
#1274
0#
#1275
1"
b1101 ,
b10000101 *
0&
1'
#1280
0"
#1285
1"
1&
b10000101 %
#1287
1#
#1290
0"
#1295
1"
b1001111 *
0&
#1300
0#
0"
#1305
1"
1&
b1001111 %
#1310
0"
#1313
1#
#1315
1"
b111011 *
0&
#1320
0"
#1325
1"
1&
b111011 %
#1326
0#
#1330
0"
#1335
1"
b111010 *
0&
#1339
1#
b1110001 )
1(
#1340
0"
#1342
b1101 +
#1345
1"
1&
b111010 %
#1350
0"
#1352
0#
#1355
1"
b1111110 *
0&
#1360
0"
#1365
1#
1"
1&
b1111110 %
0(
0'
#1370
0"
#1375
1"
b1110 ,
b10101 *
0&
1'
#1378
0#
#1380
0"
#1385
1"
1&
b10101 %
#1390
0"
#1391
1#
#1395
1"
b11110001 *
0&
#1400
0"
#1404
0#
#1405
1"
1&
b11110001 %
#1410
0"
#1415
1"
b11011001 *
0&
#1417
1#
#1420
0"
#1425
1"
1&
b11011001 %
#1430
0#
0"
#1435
1"
b1100010 *
0&
#1440
0"
#1443
1#
b1111110 )
1(
#1445
1"
1&
b1100010 %
#1446
b1110 +
#1450
0"
#1455
1"
b1001100 *
0&
#1456
0#
#1460
0"
#1465
1"
1&
b1001100 %
0'
#1469
1#
0(
#1470
0"
#1475
1"
b1111 ,
b10011111 *
0&
1'
#1480
0"
#1482
0#
#1485
1"
1&
b10011111 %
#1490
0"
#1495
1#
1"
b10001111 *
0&
#1500
0"
#1505
1"
1&
b10001111 %
#1508
0#
#1510
0"
#1515
1"
b11111000 *
0&
#1520
0"
#1521
1#
#1525
1"
1&
b11111000 %
#1530
0"
#1534
0#
#1535
1"
b10110111 *
0&
#1540
0"
#1545
1"
1&
b10110111 %
#1547
1#
b1001100 )
1(
#1550
0"
b1111 +
#1555
1"
b10011111 *
0&
#1560
0#
0"
#1565
1"
1&
b10011111 %
#1570
0"
#1573
1#
0(
#1575
1"
b1011100 *
0&
0'
#1580
0"
#1585
1"
1&
b1011100 %
#1586
0#
#1590
0"
#1595
1"
b10000 ,
b1011011 *
0&
1'
#1599
1#
#1600
0"
#1605
1"
1&
b1011011 %
#1610
0"
#1612
0#
#1615
1"
b10001001 *
0&
#1620
0"
#1625
1#
1"
1&
b10001001 %
#1630
0"
#1635
1"
b1001001 *
0&
#1638
0#
#1640
0"
#1645
1"
1&
b1001001 %
#1650
0"
#1651
1#
b1011100 )
1(
#1654
b10000 +
#1655
1"
b11010000 *
0&
#1660
0"
#1664
0#
#1665
1"
1&
b11010000 %
#1670
0"
#1675
1"
b11010111 *
0&
0'
#1677
1#
0(
#1680
0"
#1685
1"
1&
b11010111 %
#1690
0#
0"
#1695
1"
b10001 ,
b1010001 *
0&
1'
#1700
0"
#1703
1#
#1705
1"
1&
b1010001 %
#1710
0"
#1715
1"
b10010110 *
0&
#1716
0#
#1720
0"
#1725
1"
1&
b10010110 %
#1729
1#
#1730
0"
#1735
1"
b1100 *
0&
#1740
0"
#1742
0#
#1745
1"
1&
b1100 %
#1750
0"
#1755
1#
1"
b11000010 *
0&
b11010111 )
1(
#1758
b10001 +
#1760
0"
#1765
1"
1&
b11000010 %
#1768
0#
#1770
0"
#1775
1"
b11001000 *
0&
#1780
0"
#1781
1#
0(
#1785
1"
1&
b11001000 %
0'
#1790
0"
#1794
0#
#1795
1"
b10010 ,
b1110111 *
0&
1'
#1800
0"
#1805
1"
1&
b1110111 %
#1807
1#
#1810
0"
#1815
1"
b111101 *
0&
#1820
0#
0"
#1825
1"
1&
b111101 %
#1830
0"
#1833
1#
#1835
1"
b10010 *
0&
#1840
0"
#1845
1"
1&
b10010 %
#1846
0#
#1850
0"
#1855
1"
b1111110 *
0&
#1859
1#
b11001000 )
1(
#1860
0"
#1862
b10010 +
#1865
1"
1&
b1111110 %
#1870
0"
#1872
0#
#1875
1"
b1101101 *
0&
#1880
0"
#1885
1#
1"
1&
b1101101 %
0(
0'
#1890
0"
#1895
1"
b10011 ,
b111001 *
0&
1'
#1898
0#
#1900
0"
#1905
1"
1&
b111001 %
#1910
0"
#1911
1#
#1915
1"
b11111 *
0&
#1920
0"
#1924
0#
#1925
1"
1&
b11111 %
#1930
0"
#1935
1"
b11010011 *
0&
#1937
1#
#1940
0"
#1945
1"
1&
b11010011 %
#1950
0#
0"
#1955
1"
b10000101 *
0&
#1960
0"
#1963
1#
b1101101 )
1(
#1965
1"
1&
b10000101 %
#1966
b10011 +
#1970
0"
#1975
1"
b1111000 *
0&
#1976
0#
#1980
0"
#1985
1"
1&
b1111000 %
0'
#1989
1#
0(
#1990
0"
#1995
1"
b10100 ,
b1011011 *
0&
1'
#2000
0"
#2002
0#
#2005
1"
1&
b1011011 %
#2010
0"
#2015
1#
1"
b1001001 *
0&
#2020
0"
#2025
1"
1&
b1001001 %
#2028
0#
#2030
0"
#2035
1"
b111111 *
0&
#2040
0"
#2041
1#
#2045
1"
1&
b111111 %
#2050
0"
#2054
0#
#2055
1"
b101010 *
0&
#2060
0"
#2065
1"
1&
b101010 %
#2067
1#
b1111000 )
1(
#2070
0"
b10100 +
#2075
1"
b1011000 *
0&
#2080
0#
0"
#2085
1"
1&
b1011000 %
#2090
0"
#2093
1#
0(
#2095
1"
b10000110 *
0&
0'
#2100
0"
#2105
1"
1&
b10000110 %
#2106
0#
#2110
0"
#2115
1"
b10101 ,
b10001110 *
0&
1'
#2119
1#
#2120
0"
#2125
1"
1&
b10001110 %
#2130
0"
#2132
0#
#2135
1"
b10011100 *
0&
#2140
0"
#2145
1#
1"
1&
b10011100 %
#2150
0"
#2155
1"
b11111010 *
0&
#2158
0#
#2160
0"
#2165
1"
1&
b11111010 %
#2170
0"
#2171
1#
b10000110 )
1(
#2174
b10101 +
#2175
1"
b100110 *
0&
#2180
0"
#2184
0#
#2185
1"
1&
b100110 %
#2190
0"
#2195
1"
b1110011 *
0&
0'
#2197
1#
0(
#2200
0"
#2205
1"
1&
b1110011 %
#2210
0#
0"
#2215
1"
b10110 ,
b10100011 *
0&
1'
#2220
0"
#2223
1#
#2225
1"
1&
b10100011 %
#2230
0"
#2235
1"
b101111 *
0&
#2236
0#
#2240
0"
#2245
1"
1&
b101111 %
#2249
1#
#2250
0"
#2255
1"
b10110011 *
0&
#2260
0"
#2262
0#
#2265
1"
1&
b10110011 %
#2270
0"
#2275
1#
1"
b1011111 *
0&
b1110011 )
1(
#2278
b10110 +
#2280
0"
#2285
1"
1&
b1011111 %
#2288
0#
#2290
0"
#2295
1"
b1000100 *
0&
#2300
0"
#2301
1#
0(
#2305
1"
1&
b1000100 %
0'
#2310
0"
#2314
0#
#2315
1"
b10111 ,
b11110111 *
0&
1'
#2320
0"
#2325
1"
1&
b11110111 %
#2327
1#
#2330
0"
#2335
1"
b11001011 *
0&
#2340
0#
0"
#2345
1"
1&
b11001011 %
#2350
0"
#2353
1#
#2355
1"
b11100110 *
0&
#2360
0"
#2365
1"
1&
b11100110 %
#2366
0#
#2370
0"
#2375
1"
b1011010 *
0&
#2379
1#
b1000100 )
1(
#2380
0"
#2382
b10111 +
#2385
1"
1&
b1011010 %
#2390
0"
#2392
0#
#2395
1"
b101001 *
0&
#2400
0"
#2405
1#
1"
1&
b101001 %
0(
0'
#2410
0"
#2415
1"
b11000 ,
b11101101 *
0&
1'
#2418
0#
#2420
0"
#2425
1"
1&
b11101101 %
#2430
0"
#2431
1#
#2435
1"
b11011010 *
0&
#2440
0"
#2444
0#
#2445
1"
1&
b11011010 %
#2450
0"
#2455
1"
b1100101 *
0&
#2457
1#
#2460
0"
#2465
1"
1&
b1100101 %
#2470
0#
0"
#2475
1"
b10110101 *
0&
#2480
0"
#2483
1#
b101001 )
1(
#2485
1"
1&
b10110101 %
#2486
b11000 +
#2490
0"
#2495
1"
b11011111 *
0&
#2496
0#
#2500
0"
#2505
1"
1&
b11011111 %
0'
#2509
1#
0(
#2510
0"
#2515
1"
b11001 ,
b1111001 *
0&
1'
#2520
0"
#2522
0#
#2525
1"
1&
b1111001 %
#2530
0"
#2535
1#
1"
b1000100 *
0&
#2540
0"
#2545
1"
1&
b1000100 %
#2548
0#
#2550
0"
#2555
1"
b11010000 *
0&
#2560
0"
#2561
1#
#2565
1"
1&
b11010000 %
#2570
0"
#2574
0#
#2575
1"
b101010 *
0&
#2580
0"
#2585
1"
1&
b101010 %
#2587
1#
b11011111 )
1(
#2590
0"
b11001 +
#2595
1"
b10101011 *
0&
#2600
0#
0"
#2605
1"
1&
b10101011 %
#2610
0"
#2613
1#
0(
#2615
1"
b1110 *
0&
0'
#2620
0"
#2625
1"
1&
b1110 %
#2626
0#
#2630
0"
#2635
1"
b11010 ,
b11011100 *
0&
1'
#2639
1#
#2640
0"
#2645
1"
1&
b11011100 %
#2650
0"
#2652
0#
#2655
1"
b10011010 *
0&
#2660
0"
#2665
1#
1"
1&
b10011010 %
#2670
0"
#2675
1"
b11111101 *
0&
#2678
0#
#2680
0"
#2685
1"
1&
b11111101 %
#2690
0"
#2691
1#
b1110 )
1(
#2694
b11010 +
#2695
1"
b11000011 *
0&
#2700
0"
#2704
0#
#2705
1"
1&
b11000011 %
#2710
0"
#2715
1"
b1010110 *
0&
0'
#2717
1#
0(
#2720
0"
#2725
1"
1&
b1010110 %
#2730
0#
0"
#2735
1"
b11011 ,
b1001110 *
0&
1'
#2740
0"
#2743
1#
#2745
1"
1&
b1001110 %
#2750
0"
#2755
1"
b1100111 *
0&
#2756
0#
#2760
0"
#2765
1"
1&
b1100111 %
#2769
1#
#2770
0"
#2775
1"
b1010 *
0&
#2780
0"
#2782
0#
#2785
1"
1&
b1010 %
#2790
0"
#2795
1#
1"
b10110110 *
0&
b1010110 )
1(
#2798
b11011 +
#2800
0"
#2805
1"
1&
b10110110 %
#2808
0#
#2810
0"
#2815
1"
b111000 *
0&
#2820
0"
#2821
1#
0(
#2825
1"
1&
b111000 %
0'
#2830
0"
#2834
0#
#2835
1"
b11100 ,
b1111001 *
0&
1'
#2840
0"
#2845
1"
1&
b1111001 %
#2847
1#
#2850
0"
#2855
1"
b10111000 *
0&
#2860
0#
0"
#2865
1"
1&
b10111000 %
#2870
0"
#2873
1#
#2875
1"
b10010100 *
0&
#2880
0"
#2885
1"
1&
b10010100 %
#2886
0#
#2890
0"
#2895
1"
b10010011 *
0&
#2899
1#
b111000 )
1(
#2900
0"
#2902
b11100 +
#2905
1"
1&
b10010011 %
#2910
0"
#2912
0#
#2915
1"
b100 *
0&
#2920
0"
#2925
1#
1"
1&
b100 %
0(
0'
#2930
0"
#2935
1"
b11101 ,
b1011001 *
0&
1'
#2938
0#
#2940
0"
#2945
1"
1&
b1011001 %
#2950
0"
#2951
1#
#2955
1"
b11011011 *
0&
#2960
0"
#2964
0#
#2965
1"
1&
b11011011 %
#2970
0"
#2975
1"
b1001101 *
0&
#2977
1#
#2980
0"
#2985
1"
1&
b1001101 %
#2990
0#
0"
#2995
1"
b11011001 *
0&
#3000
0"
#3003
1#
b100 )
1(
#3005
1"
1&
b11011001 %
#3006
b11101 +
#3010
0"
#3015
1"
b1101101 *
0&
#3016
0#
#3020
0"
#3025
1"
1&
b1101101 %
0'
#3029
1#
0(
#3030
0"
#3035
1"
b11110 ,
b1110110 *
0&
1'
#3040
0"
#3042
0#
#3045
1"
1&
b1110110 %
#3050
0"
#3055
1#
1"
b11001010 *
0&
#3060
0"
#3065
1"
1&
b11001010 %
#3068
0#
#3070
0"
#3075
1"
b10110110 *
0&
#3080
0"
#3081
1#
#3085
1"
1&
b10110110 %
#3090
0"
#3094
0#
#3095
1"
b10010101 *
0&
#3100
0"
#3105
1"
1&
b10010101 %
#3107
1#
b1101101 )
1(
#3110
0"
b11110 +
#3115
1"
b1000110 *
0&
#3120
0#
0"
#3125
1"
1&
b1000110 %
#3130
0"
#3133
1#
0(
#3135
1"
b100 *
0&
0'
#3140
0"
#3145
1"
1&
b100 %
#3146
0#
#3150
0"
#3155
1"
b11111 ,
b11110111 *
0&
1'
#3159
1#
#3160
0"
#3165
1"
1&
b11110111 %
#3170
0"
#3172
0#
#3175
1"
b1101001 *
0&
#3180
0"
#3185
1#
1"
1&
b1101001 %
#3190
0"
#3195
1"
b10110100 *
0&
#3198
0#
#3200
0"
#3205
1"
1&
b10110100 %
#3210
0"
#3211
1#
b100 )
1(
#3214
b11111 +
#3215
1"
b10001000 *
0&
#3220
0"
#3224
0#
#3225
1"
1&
b10001000 %
#3230
0"
#3235
1"
b101000 *
0&
0'
#3237
1#
0(
#3240
0"
#3245
1"
1&
b101000 %
#3250
0#
0"
#3255
1"
b100000 ,
b101101 *
0&
1'
#3260
0"
#3263
1#
#3265
1"
1&
b101101 %
#3270
0"
#3275
1"
b11000111 *
0&
#3276
0#
#3280
0"
#3285
1"
1&
b11000111 %
#3289
1#
#3290
0"
#3295
1"
b101110 *
0&
#3300
0"
#3302
0#
#3305
1"
1&
b101110 %
#3310
0"
#3315
1#
1"
b1000 *
0&
b101000 )
1(
#3318
b100000 +
#3320
0"
#3325
1"
1&
b1000 %
#3328
0#
#3330
0"
#3335
1"
b11100 *
0&
#3340
0"
#3341
1#
0(
#3345
1"
1&
b11100 %
0'
#3350
0"
#3354
0#
#3355
1"
b100001 ,
b11111101 *
0&
1'
#3360
0"
#3365
1"
1&
b11111101 %
#3367
1#
#3370
0"
#3375
1"
b101001 *
0&
#3380
0#
0"
#3385
1"
1&
b101001 %
#3390
0"
#3393
1#
#3395
1"
b11100 *
0&
#3400
0"
#3405
1"
1&
b11100 %
#3406
0#
#3410
0"
#3415
1"
b10000110 *
0&
#3419
1#
b11100 )
1(
#3420
0"
#3422
b100001 +
#3425
1"
1&
b10000110 %
#3430
0"
#3432
0#
#3435
1"
b11011010 *
0&
#3440
0"
#3445
1#
1"
1&
b11011010 %
0(
0'
#3450
0"
#3455
1"
b100010 ,
b111101 *
0&
1'
#3458
0#
#3460
0"
#3465
1"
1&
b111101 %
#3470
0"
#3471
1#
#3475
1"
b1100110 *
0&
#3480
0"
#3484
0#
#3485
1"
1&
b1100110 %
#3490
0"
#3495
1"
b1110000 *
0&
#3497
1#
#3500
0"
#3505
1"
1&
b1110000 %
#3510
0#
0"
#3515
1"
b1110011 *
0&
#3520
0"
#3523
1#
b11011010 )
1(
#3525
1"
1&
b1110011 %
#3526
b100010 +
#3530
0"
#3535
1"
b10111010 *
0&
#3536
0#
#3540
0"
#3545
1"
1&
b10111010 %
0'
#3549
1#
0(
#3550
0"
#3555
1"
b100011 ,
b1011110 *
0&
1'
#3560
0"
#3562
0#
#3565
1"
1&
b1011110 %
#3570
0"
#3575
1#
1"
b11111010 *
0&
#3580
0"
#3585
1"
1&
b11111010 %
#3588
0#
#3590
0"
#3595
1"
b11010101 *
0&
#3600
0"
#3601
1#
#3605
1"
1&
b11010101 %
#3610
0"
#3614
0#
#3615
1"
b11010 *
0&
#3620
0"
#3625
1"
1&
b11010 %
#3627
1#
b10111010 )
1(
#3630
0"
b100011 +
#3635
1"
b10111001 *
0&
#3640
0#
0"
#3645
1"
1&
b10111001 %
#3650
0"
#3653
1#
0(
#3655
1"
b110111 *
0&
0'
#3660
0"
#3665
1"
1&
b110111 %
#3666
0#
#3670
0"
#3675
1"
b100100 ,
b10010110 *
0&
1'
#3679
1#
#3680
0"
#3685
1"
1&
b10010110 %
#3690
0"
#3692
0#
#3695
1"
b11000000 *
0&
#3700
0"
#3705
1#
1"
1&
b11000000 %
#3710
0"
#3715
1"
b100110 *
0&
#3718
0#
#3720
0"
#3725
1"
1&
b100110 %
#3730
0"
#3731
1#
b110111 )
1(
#3734
b100100 +
#3735
1"
b10110110 *
0&
#3740
0"
#3744
0#
#3745
1"
1&
b10110110 %
#3750
0"
#3755
1"
b1111101 *
0&
0'
#3757
1#
0(
#3760
0"
#3765
1"
1&
b1111101 %
#3770
0#
0"
#3775
1"
b100101 ,
b11011100 *
0&
1'
#3780
0"
#3783
1#
#3785
1"
1&
b11011100 %
#3790
0"
#3795
1"
b10000110 *
0&
#3796
0#
#3800
0"
#3805
1"
1&
b10000110 %
#3809
1#
#3810
0"
#3815
1"
b1111000 *
0&
#3820
0"
